{
	"portGroup":3,
	"ip":"127.0.0.1",
	"host":"127.0.0.1",
	"mysql":
	{
		"user":"root",
		"password":"123456"
	},
	"rootMysql":
	{
		"user":"root",
		"password":"123456"
	},
	"authServer":
	{
		"database":"GlobalUser"
	},
	"game_server":
	{
		"database":
		{
			"GameUser":"GameUser",
			"GameStat":"GameStat",
			"GameLog":"GameLog"
		},
		"authPaltforms":
		{
			"default":"default"
		},
		"stateReport":
		{
			"serverName":"game",
			"alias":"test"			
		}
	},
	"serverManager":
	{
		"portGroup":-1,
		"host":"-",	
		"databaseName":"serverManager",
		"mysql":
		{
			"user":"-",
			"password":"-" 
		},
		"orderPaltforms":
		{
			"default":"default",
			"uc":"uc"
		}
	},
	"SnExchangeServer":
	{
		"portGroup":-1,
		"host":"-",	
		"databaseName":"SNExchange",
		"mysql":
		{
			"user":"-",
			"password":"-" 
		}
	},
    "gmServer":
    {
        "portGroup":-1,
        "host":"-",
        "databaseName":"GameAdmin",
        "mysql":
        {
            "user":"-",
            "password":"-"
        }
    }
}
